duckdbmcp/__init__.py
duckdbmcp/config.py
duckdbmcp/server.py
duckdbmcp/lib/handler.py
duckdbmcp-0.0.34.dist-info/METADATA
duckdbmcp-0.0.34.dist-info/WHEEL
duckdbmcp-0.0.34.dist-info/entry_points.txt
duckdbmcp-0.0.34.dist-info/licenses/LICENSE
duckdbmcp-0.0.34.dist-info/RECORD
